README.txt
bootstrap.py
buildout.cfg
setup.cfg
setup.py
wtforms_extras/__init__.py
wtforms_extras.egg-info/PKG-INFO
wtforms_extras.egg-info/SOURCES.txt
wtforms_extras.egg-info/dependency_links.txt
wtforms_extras.egg-info/entry_points.txt
wtforms_extras.egg-info/not-zip-safe
wtforms_extras.egg-info/requires.txt
wtforms_extras.egg-info/top_level.txt
wtforms_extras/templates/bootstrap/default.pt
wtforms_extras/templates/default/default.pt
wtforms_extras/templates/default/form.pt
wtforms_extras/templates/foundation/default.pt
wtforms_extras/templates/foundation/form.pt
wtforms_extras/templates/foundation/submitfield.pt
wtforms_extras/tests/__init__.py
wtforms_extras/tests/test_fields.py
wtforms_extras/tests/test_form.py