Metadata-Version: 1.0
Name: wtforms-extras
Version: 1.1.4
Summary: Provide templates for wtform widgets
Home-page: https://github.com/vangheem/wtform_extras
Author: Nathan Van Gheem
Author-email: nathan@vangheem.us
License: MIT
Keywords: wtform form widgets
Platform: UNKNOWN
